{
  "/": {
    "testids": [
      "add-menu-caret",
      "add-transaction-btn",
      "dash-*",
      "help-button",
      "hero-add-account",
      "hero-add-txn",
      "hero-quote-enable",
      "member-*",
      "period-pill",
      "profile-switch-btn",
      "sample-dismiss",
      "sample-start-fresh",
      "smart-action-SMART-*",
      "smart-dismiss",
      "smart-strip-toggle",
      "smart-strip-viewall",
      "theme-toggle",
      "topbar-*",
      "topbar-more"
    ],
    "untestided": 139
  },
  "/transactions": {
    "testids": [
      "add-menu-caret",
      "add-transaction-btn",
      "help-button",
      "member-*",
      "period-pill",
      "profile-switch-btn",
      "sample-dismiss",
      "sample-start-fresh",
      "smart-action-SMART-*",
      "smart-dismiss",
      "smart-strip-toggle",
      "smart-strip-viewall",
      "theme-toggle",
      "topbar-*",
      "topbar-more",
      "txn-add-btn",
      "txn-dupes-btn",
      "txn-import-btn",
      "txn-row-receipt"
    ],
    "untestided": 75
  },
  "/accounts": {
    "testids": [
      "acct-liabilities-stub",
      "add-menu-caret",
      "add-transaction-btn",
      "creds-start-btn-acct-*",
      "creds-start-btn-acct-cash",
      "creds-start-btn-acct-home",
      "creds-start-btn-acct-hysa",
      "creds-start-btn-acct-roth",
      "delete-account-btn-acct-*",
      "delete-account-btn-acct-cash",
      "delete-account-btn-acct-home",
      "delete-account-btn-acct-hysa",
      "delete-account-btn-acct-roth",
      "help-button",
      "member-*",
      "page-transfer-btn",
      "profile-switch-btn",
      "reconcile-start-btn-acct-*",
      "reconcile-start-btn-acct-cash",
      "reconcile-start-btn-acct-home",
      "reconcile-start-btn-acct-hysa",
      "reconcile-start-btn-acct-roth",
      "sample-dismiss",
      "sample-start-fresh",
      "set-institution-acct-*",
      "set-institution-acct-cash",
      "set-institution-acct-home",
      "set-institution-acct-hysa",
      "set-institution-acct-roth",
      "smart-action-SMART-*",
      "smart-badge-SMART-*",
      "smart-dismiss",
      "smart-section-action",
      "smart-strip-toggle",
      "smart-strip-viewall",
      "theme-toggle",
      "topbar-*",
      "topbar-more",
      "transfer-start-btn-acct-*",
      "transfer-start-btn-acct-cash",
      "transfer-start-btn-acct-home",
      "transfer-start-btn-acct-hysa",
      "transfer-start-btn-acct-roth"
    ],
    "untestided": 70
  },
  "/budgets": {
    "testids": [
      "add-menu-caret",
      "add-transaction-btn",
      "budget-cover-btn-bud-*",
      "budget-topup-btn-bud-*",
      "budget-topup-btn-bud-baby",
      "budget-topup-btn-bud-dining",
      "budget-topup-btn-bud-fun",
      "budget-topup-btn-bud-subs",
      "budget-topup-btn-bud-travel",
      "budget-topup-btn-bud-vices",
      "budget-view-txns-bud-*",
      "budget-view-txns-bud-baby",
      "budget-view-txns-bud-dining",
      "budget-view-txns-bud-fun",
      "budget-view-txns-bud-subs",
      "budget-view-txns-bud-travel",
      "budget-view-txns-bud-vices",
      "budgets-add",
      "budgets-method",
      "budgets-template-*",
      "budgets-toggle-*",
      "delete-budget-btn-bud-*",
      "delete-budget-btn-bud-baby",
      "delete-budget-btn-bud-dining",
      "delete-budget-btn-bud-fun",
      "delete-budget-btn-bud-subs",
      "delete-budget-btn-bud-travel",
      "delete-budget-btn-bud-vices",
      "edit-budget-btn-bud-*",
      "edit-budget-btn-bud-baby",
      "edit-budget-btn-bud-dining",
      "edit-budget-btn-bud-fun",
      "edit-budget-btn-bud-subs",
      "edit-budget-btn-bud-travel",
      "edit-budget-btn-bud-vices",
      "help-button",
      "member-*",
      "period-pill",
      "profile-switch-btn",
      "sample-dismiss",
      "sample-start-fresh",
      "smart-action-SMART-*",
      "smart-dismiss",
      "smart-section-action",
      "smart-strip-toggle",
      "smart-strip-viewall",
      "theme-toggle",
      "topbar-*",
      "topbar-more"
    ],
    "untestided": 46
  },
  "/goals": {
    "testids": [
      "add-menu-caret",
      "add-transaction-btn",
      "goal-contribute-goal-*",
      "goal-contribute-goal-baby",
      "goal-contribute-goal-car",
      "goal-contribute-goal-house",
      "goal-delete-btn-goal-*",
      "goal-delete-btn-goal-baby",
      "goal-delete-btn-goal-car",
      "goal-delete-btn-goal-house",
      "goal-edit-btn-goal-*",
      "goal-edit-btn-goal-baby",
      "goal-edit-btn-goal-car",
      "goal-edit-btn-goal-house",
      "goal-menu-btn-goal-*",
      "goal-menu-btn-goal-baby",
      "goal-menu-btn-goal-car",
      "goal-menu-btn-goal-house",
      "goal-todo-check-task-*",
      "goal-todo-check-task-baby-budget",
      "goal-todo-check-task-h-*",
      "goal-todo-check-task-h-crib",
      "goals-add",
      "goals-toggle-*",
      "help-button",
      "member-*",
      "profile-switch-btn",
      "sample-dismiss",
      "sample-start-fresh",
      "smart-action-SMART-*",
      "smart-dismiss",
      "smart-section-action",
      "smart-strip-toggle",
      "smart-strip-viewall",
      "theme-toggle",
      "topbar-*",
      "topbar-more"
    ],
    "untestided": 19
  },
  "/todo": {
    "testids": [
      "add-menu-caret",
      "add-transaction-btn",
      "help-button",
      "member-*",
      "profile-switch-btn",
      "sample-dismiss",
      "sample-start-fresh",
      "smart-action-SMART-*",
      "smart-dismiss",
      "smart-strip-viewall",
      "task-addsub-task-*",
      "task-addsub-task-baby-budget",
      "task-addsub-task-card",
      "task-addsub-task-dining-budget",
      "task-addsub-task-h-*",
      "task-addsub-task-h-carseat",
      "task-addsub-task-h-crib",
      "task-addsub-task-h-faucet",
      "task-addsub-task-h-filters",
      "task-addsub-task-h-freezer",
      "task-addsub-task-h-garage",
      "task-addsub-task-h-hvac",
      "task-addsub-task-h-nursery-paint",
      "task-addsub-task-h-smoke",
      "task-addsub-task-maternity-leave",
      "task-check-task-*",
      "task-check-task-baby-budget",
      "task-check-task-card",
      "task-check-task-dining-budget",
      "task-check-task-h-*",
      "task-check-task-h-carseat",
      "task-check-task-h-crib",
      "task-check-task-h-faucet",
      "task-check-task-h-filters",
      "task-check-task-h-freezer",
      "task-check-task-h-garage",
      "task-check-task-h-hvac",
      "task-check-task-h-nursery-paint",
      "task-check-task-h-smoke",
      "task-check-task-maternity-leave",
      "task-delete-btn-task-*",
      "task-delete-btn-task-baby-budget",
      "task-delete-btn-task-card",
      "task-delete-btn-task-dining-budget",
      "task-delete-btn-task-h-*",
      "task-delete-btn-task-h-carseat",
      "task-delete-btn-task-h-crib",
      "task-delete-btn-task-h-faucet",
      "task-delete-btn-task-h-filters",
      "task-delete-btn-task-h-freezer",
      "task-delete-btn-task-h-garage",
      "task-delete-btn-task-h-hvac",
      "task-delete-btn-task-h-nursery-paint",
      "task-delete-btn-task-h-smoke",
      "task-delete-btn-task-maternity-leave",
      "task-edit-btn-task-*",
      "task-edit-btn-task-baby-budget",
      "task-edit-btn-task-card",
      "task-edit-btn-task-dining-budget",
      "task-edit-btn-task-h-*",
      "task-edit-btn-task-h-carseat",
      "task-edit-btn-task-h-crib",
      "task-edit-btn-task-h-faucet",
      "task-edit-btn-task-h-filters",
      "task-edit-btn-task-h-freezer",
      "task-edit-btn-task-h-garage",
      "task-edit-btn-task-h-hvac",
      "task-edit-btn-task-h-nursery-paint",
      "task-edit-btn-task-h-smoke",
      "task-edit-btn-task-maternity-leave",
      "task-link-task-*",
      "task-link-task-baby-budget",
      "task-link-task-card",
      "task-link-task-dining-budget",
      "task-link-task-h-crib",
      "task-menu-btn-task-*",
      "task-menu-btn-task-baby-budget",
      "task-menu-btn-task-card",
      "task-menu-btn-task-dining-budget",
      "task-menu-btn-task-h-*",
      "task-menu-btn-task-h-carseat",
      "task-menu-btn-task-h-crib",
      "task-menu-btn-task-h-faucet",
      "task-menu-btn-task-h-filters",
      "task-menu-btn-task-h-freezer",
      "task-menu-btn-task-h-garage",
      "task-menu-btn-task-h-hvac",
      "task-menu-btn-task-h-nursery-paint",
      "task-menu-btn-task-h-smoke",
      "task-menu-btn-task-maternity-leave",
      "theme-toggle",
      "todo-add",
      "todo-filter-prio",
      "todo-hide-done",
      "todo-next",
      "todo-prev",
      "todo-sort",
      "topbar-*",
      "topbar-more"
    ],
    "untestided": 15
  },
  "/notifications": {
    "testids": [
      "add-menu-caret",
      "add-transaction-btn",
      "help-button",
      "member-*",
      "notif-clear-all",
      "notif-dismiss-default-backup@backup@2026-*",
      "notif-dismiss-default-bill-due@acct-carloan-marcus@2026-07-*",
      "notif-dismiss-default-bill-due@acct-carloan-priya@2026-07-*",
      "notif-dismiss-default-bill-due@acct-studentloan@2026-07-*",
      "notif-dismiss-default-digest@digest@2026-*",
      "notif-dismiss-default-large@txn:tx-2026-06-getaway",
      "notif-dismiss-default-stale@acct-card@2026-*",
      "notif-dismiss-default-stale@acct-carloan-marcus@2026-*",
      "notif-dismiss-default-stale@acct-carloan-priya@2026-*",
      "notif-dismiss-default-stale@acct-cash@2026-*",
      "notif-dismiss-default-stale@acct-studentloan@2026-*",
      "notif-dismiss-default-stale@acct-travelcard@2026-*",
      "notif-dismiss-digest:2026-07-*",
      "notif-filter",
      "notif-open-default-bill-due@acct-carloan-marcus@2026-07-*",
      "notif-open-default-bill-due@acct-carloan-priya@2026-07-*",
      "notif-open-default-bill-due@acct-studentloan@2026-07-*",
      "notif-open-default-digest@digest@2026-*",
      "notif-open-default-large@txn:tx-2026-06-getaway",
      "notif-open-default-stale@acct-card@2026-*",
      "notif-open-default-stale@acct-carloan-marcus@2026-*",
      "notif-open-default-stale@acct-carloan-priya@2026-*",
      "notif-open-default-stale@acct-cash@2026-*",
      "notif-open-default-stale@acct-studentloan@2026-*",
      "notif-open-default-stale@acct-travelcard@2026-*",
      "notif-read-default-backup@backup@2026-*",
      "notif-read-default-bill-due@acct-carloan-marcus@2026-07-*",
      "notif-read-default-bill-due@acct-carloan-priya@2026-07-*",
      "notif-read-default-bill-due@acct-studentloan@2026-07-*",
      "notif-read-default-digest@digest@2026-*",
      "notif-read-default-large@txn:tx-2026-06-getaway",
      "notif-read-default-stale@acct-card@2026-*",
      "notif-read-default-stale@acct-carloan-marcus@2026-*",
      "notif-read-default-stale@acct-carloan-priya@2026-*",
      "notif-read-default-stale@acct-cash@2026-*",
      "notif-read-default-stale@acct-studentloan@2026-*",
      "notif-read-default-stale@acct-travelcard@2026-*",
      "notif-read-digest:2026-07-*",
      "notif-snooze-default-backup@backup@2026-*",
      "notif-snooze-default-bill-due@acct-carloan-marcus@2026-07-*",
      "notif-snooze-default-bill-due@acct-carloan-priya@2026-07-*",
      "notif-snooze-default-bill-due@acct-studentloan@2026-07-*",
      "notif-snooze-default-digest@digest@2026-*",
      "notif-snooze-default-large@txn:tx-2026-06-getaway",
      "notif-snooze-default-stale@acct-card@2026-*",
      "notif-snooze-default-stale@acct-carloan-marcus@2026-*",
      "notif-snooze-default-stale@acct-carloan-priya@2026-*",
      "notif-snooze-default-stale@acct-cash@2026-*",
      "notif-snooze-default-stale@acct-studentloan@2026-*",
      "notif-snooze-default-stale@acct-travelcard@2026-*",
      "notif-snooze-digest:2026-07-*",
      "profile-switch-btn",
      "sample-dismiss",
      "sample-start-fresh",
      "theme-toggle",
      "topbar-*",
      "topbar-more"
    ],
    "untestided": 15
  },
  "/debt": {
    "testids": [
      "add-menu-caret",
      "add-transaction-btn",
      "credit-limit-edit-acct-*",
      "credit-limit-edit-acct-card",
      "debt-add",
      "debt-edit-acct-*",
      "debt-edit-acct-card",
      "debt-edit-acct-carloan-marcus",
      "debt-edit-acct-carloan-priya",
      "debt-jump-sec-*",
      "debt-jump-sec-credit",
      "debt-jump-sec-ladder",
      "debt-jump-sec-loans",
      "debt-link-/accounts",
      "debt-link-/allocate",
      "debt-link-/networth",
      "debt-link-/planning",
      "debt-payoff-toggle-acct-*",
      "debt-payoff-toggle-acct-card",
      "debt-payoff-toggle-acct-carloan-marcus",
      "debt-payoff-toggle-acct-carloan-priya",
      "debt-toggle-*",
      "debt-view-acct-*",
      "debt-view-acct-card",
      "debt-view-acct-carloan-marcus",
      "debt-view-acct-carloan-priya",
      "help-button",
      "member-*",
      "profile-switch-btn",
      "sample-dismiss",
      "sample-start-fresh",
      "strat-extra",
      "theme-toggle",
      "topbar-*",
      "topbar-more"
    ],
    "untestided": 30
  },
  "/investments": {
    "testids": [
      "add-menu-caret",
      "add-transaction-btn",
      "help-button",
      "holding-close-hold-401k-tdf",
      "holding-close-hold-roth-vti",
      "holding-close-hold-wsb-gme",
      "holding-close-hold-wsb-nvda",
      "holding-close-hold-wsb-pltr",
      "holding-close-hold-wsb-tsla",
      "holding-del-hold-401k-tdf",
      "holding-del-hold-roth-vti",
      "holding-del-hold-wsb-gme",
      "holding-del-hold-wsb-nvda",
      "holding-del-hold-wsb-pltr",
      "holding-del-hold-wsb-tsla",
      "holding-menu-btn-hold-401k-tdf",
      "holding-menu-btn-hold-roth-vti",
      "holding-menu-btn-hold-wsb-gme",
      "holding-menu-btn-hold-wsb-nvda",
      "holding-menu-btn-hold-wsb-pltr",
      "holding-menu-btn-hold-wsb-tsla",
      "invest-acct-view-acct-*",
      "invest-acct-view-acct-roth",
      "invest-add",
      "invest-growth-*",
      "invest-link-/accounts",
      "invest-link-/networth",
      "invest-new-pool",
      "invest-toggle-*",
      "member-*",
      "profile-switch-btn",
      "sample-dismiss",
      "sample-start-fresh",
      "theme-toggle",
      "topbar-*",
      "topbar-more"
    ],
    "untestided": 16
  },
  "/allocate": {
    "testids": [
      "add-menu-caret",
      "add-transaction-btn",
      "alloc-exclude-acct-*",
      "alloc-exclude-acct-card",
      "alloc-exclude-acct-carloan-marcus",
      "alloc-exclude-acct-carloan-priya",
      "alloc-exclude-acct-cash",
      "alloc-exclude-acct-home",
      "alloc-exclude-acct-hysa",
      "alloc-exclude-acct-roth",
      "alloc-exclude-goal:goal-*",
      "alloc-exclude-goal:goal-baby",
      "alloc-exclude-goal:goal-car",
      "alloc-exclude-goal:goal-house",
      "alloc-menu-acct-*",
      "alloc-menu-acct-card",
      "alloc-menu-acct-carloan-marcus",
      "alloc-menu-acct-carloan-priya",
      "alloc-menu-acct-cash",
      "alloc-menu-acct-home",
      "alloc-menu-acct-hysa",
      "alloc-menu-acct-roth",
      "alloc-menu-goal:goal-*",
      "alloc-menu-goal:goal-baby",
      "alloc-menu-goal:goal-car",
      "alloc-menu-goal:goal-house",
      "alloc-source-acct-*",
      "alloc-source-acct-card",
      "alloc-source-acct-carloan-marcus",
      "alloc-source-acct-carloan-priya",
      "alloc-source-acct-cash",
      "alloc-source-acct-home",
      "alloc-source-acct-hysa",
      "alloc-source-acct-roth",
      "alloc-source-goal:goal-*",
      "alloc-source-goal:goal-baby",
      "alloc-source-goal:goal-car",
      "alloc-source-goal:goal-house",
      "allocate-amount",
      "allocate-edit-*",
      "allocate-explain",
      "allocate-toggle-*",
      "help-button",
      "income-nudge-apply",
      "invest-link-/accounts",
      "member-*",
      "profile-switch-btn",
      "sample-dismiss",
      "sample-start-fresh",
      "smart-action-SMART-*",
      "smart-dismiss",
      "smart-strip-toggle",
      "smart-strip-viewall",
      "theme-toggle",
      "topbar-*",
      "topbar-more"
    ],
    "untestided": 17
  },
  "/planning": {
    "testids": [
      "add-menu-caret",
      "add-transaction-btn",
      "help-button",
      "member-*",
      "period-pill",
      "plan-add-open",
      "plan-compare-select",
      "plan-del-plan-card-payoff",
      "plan-del-plan-house",
      "plan-del-plan-jobloss",
      "plan-menu-plan-card-payoff",
      "plan-menu-plan-house",
      "plan-menu-plan-jobloss",
      "planning-toggle-*",
      "profile-switch-btn",
      "sample-dismiss",
      "sample-start-fresh",
      "smart-action-SMART-*",
      "smart-dismiss",
      "smart-section-action",
      "smart-strip-toggle",
      "smart-strip-viewall",
      "theme-toggle",
      "topbar-*",
      "topbar-more"
    ],
    "untestided": 35
  },
  "/recurring": {
    "testids": [
      "add-menu-caret",
      "add-transaction-btn",
      "detected-add",
      "help-button",
      "member-*",
      "profile-switch-btn",
      "recurring-add",
      "recurring-del-rec-*",
      "recurring-del-rec-bizsoft",
      "recurring-del-rec-carpay-m",
      "recurring-del-rec-carpay-p",
      "recurring-del-rec-gym",
      "recurring-del-rec-hoa",
      "recurring-del-rec-homeins",
      "recurring-del-rec-proptax-fall",
      "recurring-del-rec-proptax-spring",
      "recurring-del-rec-salary",
      "recurring-del-rec-subs",
      "recurring-edit-rec-*",
      "recurring-edit-rec-bizsoft",
      "recurring-edit-rec-carpay-m",
      "recurring-edit-rec-carpay-p",
      "recurring-edit-rec-gym",
      "recurring-edit-rec-hoa",
      "recurring-edit-rec-homeins",
      "recurring-edit-rec-proptax-fall",
      "recurring-edit-rec-proptax-spring",
      "recurring-edit-rec-salary",
      "recurring-edit-rec-subs",
      "recurring-menu-rec-*",
      "recurring-menu-rec-bizsoft",
      "recurring-menu-rec-carpay-m",
      "recurring-menu-rec-carpay-p",
      "recurring-menu-rec-gym",
      "recurring-menu-rec-hoa",
      "recurring-menu-rec-homeins",
      "recurring-menu-rec-proptax-fall",
      "recurring-menu-rec-proptax-spring",
      "recurring-menu-rec-salary",
      "recurring-menu-rec-subs",
      "recurring-post-due",
      "recurring-tab-*",
      "recurring-tab-bills",
      "recurring-toggle-*",
      "recurring-viewacct-rec-*",
      "recurring-viewacct-rec-bizsoft",
      "recurring-viewacct-rec-carpay-m",
      "recurring-viewacct-rec-carpay-p",
      "recurring-viewacct-rec-gym",
      "recurring-viewacct-rec-hoa",
      "recurring-viewacct-rec-homeins",
      "recurring-viewacct-rec-proptax-fall",
      "recurring-viewacct-rec-proptax-spring",
      "recurring-viewacct-rec-salary",
      "recurring-viewacct-rec-subs",
      "recurring-viewbudget-rec-subs",
      "recurring-viewtxns-rec-*",
      "recurring-viewtxns-rec-bizsoft",
      "recurring-viewtxns-rec-carpay-m",
      "recurring-viewtxns-rec-carpay-p",
      "recurring-viewtxns-rec-gym",
      "recurring-viewtxns-rec-hoa",
      "recurring-viewtxns-rec-homeins",
      "recurring-viewtxns-rec-proptax-fall",
      "recurring-viewtxns-rec-proptax-spring",
      "recurring-viewtxns-rec-salary",
      "recurring-viewtxns-rec-subs",
      "sample-dismiss",
      "sample-start-fresh",
      "theme-toggle",
      "topbar-*",
      "topbar-more"
    ],
    "untestided": 15
  },
  "/reports": {
    "testids": [
      "add-menu-caret",
      "add-transaction-btn",
      "expenses-drill",
      "help-button",
      "income-drill",
      "member-*",
      "moneyflow-drill",
      "payees-drill",
      "period-pill",
      "profile-switch-btn",
      "reports-export-*",
      "reports-export-income",
      "reports-export-largest",
      "reports-export-member",
      "reports-export-payees",
      "reports-export-pdf",
      "reports-export-tax",
      "reports-export-toggle",
      "reports-scope-toggle",
      "reports-toggle-*",
      "sample-dismiss",
      "sample-start-fresh",
      "theme-toggle",
      "topbar-*",
      "topbar-more"
    ],
    "untestided": 31
  },
  "/networth": {
    "testids": [
      "add-menu-caret",
      "add-transaction-btn",
      "help-button",
      "member-*",
      "networth-drill",
      "nw-accounts-link",
      "nw-debt-link",
      "nw-owe-drill",
      "nw-toggle-*",
      "profile-switch-btn",
      "sample-dismiss",
      "sample-start-fresh",
      "theme-toggle",
      "topbar-*",
      "topbar-more"
    ],
    "untestided": 18
  },
  "/health": {
    "testids": [
      "add-menu-caret",
      "add-transaction-btn",
      "health-step",
      "health-toggle-*",
      "help-button",
      "hf-act-*",
      "hf-act-budget",
      "hf-act-debt",
      "hf-act-nw-trend",
      "hf-act-savings",
      "member-*",
      "profile-switch-btn",
      "sample-dismiss",
      "sample-start-fresh",
      "theme-toggle",
      "topbar-*",
      "topbar-more"
    ],
    "untestided": 15
  },
  "/assistant": {
    "testids": [
      "add-menu-caret",
      "add-transaction-btn",
      "assistant-*",
      "assistant-new-chat",
      "assistant-see-*",
      "assistant-send",
      "help-button",
      "member-*",
      "profile-switch-btn",
      "sample-dismiss",
      "sample-start-fresh",
      "theme-toggle",
      "topbar-*",
      "topbar-more"
    ],
    "untestided": 37
  },
  "/studio": {
    "testids": [
      "add-menu-caret",
      "add-transaction-btn",
      "help-button",
      "member-*",
      "profile-switch-btn",
      "sample-dismiss",
      "sample-start-fresh",
      "theme-toggle",
      "topbar-*",
      "topbar-more"
    ],
    "untestided": 48
  },
  "/household": {
    "testids": [
      "add-menu-caret",
      "add-transaction-btn",
      "help-button",
      "member-*",
      "member-delete-m-marcus",
      "member-delete-m-priya",
      "member-make-default-m-priya",
      "member-menu-btn-m-marcus",
      "member-menu-btn-m-priya",
      "member-set-pin-m-marcus",
      "member-set-pin-m-priya",
      "member-view-m-marcus",
      "member-view-m-priya",
      "profile-switch-btn",
      "sample-dismiss",
      "sample-start-fresh",
      "theme-toggle",
      "topbar-*",
      "topbar-more"
    ],
    "untestided": 21
  },
  "/categories": {
    "testids": [
      "add-menu-caret",
      "add-transaction-btn",
      "cat-delete-cat-*",
      "cat-delete-cat-baby",
      "cat-delete-cat-business-expense",
      "cat-delete-cat-business-income",
      "cat-delete-cat-car-*",
      "cat-delete-cat-dining",
      "cat-delete-cat-fees",
      "cat-delete-cat-gas",
      "cat-delete-cat-gifts",
      "cat-delete-cat-health",
      "cat-delete-cat-hoa",
      "cat-delete-cat-home-*",
      "cat-delete-cat-housing",
      "cat-delete-cat-investing-income",
      "cat-delete-cat-investing-loss",
      "cat-delete-cat-other-income",
      "cat-delete-cat-salary",
      "cat-delete-cat-travel",
      "cat-delete-cat-vices",
      "cat-menu-btn-cat-*",
      "cat-menu-btn-cat-baby",
      "cat-menu-btn-cat-business-expense",
      "cat-menu-btn-cat-business-income",
      "cat-menu-btn-cat-car-*",
      "cat-menu-btn-cat-dining",
      "cat-menu-btn-cat-fees",
      "cat-menu-btn-cat-gas",
      "cat-menu-btn-cat-gifts",
      "cat-menu-btn-cat-health",
      "cat-menu-btn-cat-hoa",
      "cat-menu-btn-cat-home-*",
      "cat-menu-btn-cat-housing",
      "cat-menu-btn-cat-investing-income",
      "cat-menu-btn-cat-investing-loss",
      "cat-menu-btn-cat-other-income",
      "cat-menu-btn-cat-salary",
      "cat-menu-btn-cat-travel",
      "cat-menu-btn-cat-vices",
      "cat-toggle-cat-*",
      "cat-toggle-cat-housing",
      "cat-view-cat-*",
      "cat-view-cat-baby",
      "cat-view-cat-business-expense",
      "cat-view-cat-business-income",
      "cat-view-cat-car-*",
      "cat-view-cat-dining",
      "cat-view-cat-fees",
      "cat-view-cat-gas",
      "cat-view-cat-gifts",
      "cat-view-cat-health",
      "cat-view-cat-hoa",
      "cat-view-cat-home-*",
      "cat-view-cat-investing-income",
      "cat-view-cat-investing-loss",
      "cat-view-cat-other-income",
      "cat-view-cat-salary",
      "cat-view-cat-travel",
      "cat-view-cat-vices",
      "categories-add",
      "help-button",
      "member-*",
      "profile-switch-btn",
      "sample-dismiss",
      "sample-start-fresh",
      "theme-toggle",
      "topbar-*",
      "topbar-more"
    ],
    "untestided": 78
  },
  "/rules": {
    "testids": [
      "add-menu-caret",
      "add-transaction-btn",
      "help-button",
      "member-*",
      "profile-switch-btn",
      "rule-delete-rule-*",
      "rule-delete-rule-amazon",
      "rule-delete-rule-coffee",
      "rule-delete-rule-shell",
      "rule-menu-btn-rule-*",
      "rule-menu-btn-rule-amazon",
      "rule-menu-btn-rule-coffee",
      "rule-menu-btn-rule-shell",
      "rule-movedown-rule-*",
      "rule-movedown-rule-amazon",
      "rule-movedown-rule-coffee",
      "rule-movedown-rule-shell",
      "rule-moveup-rule-*",
      "rule-moveup-rule-amazon",
      "rule-moveup-rule-coffee",
      "rule-moveup-rule-shell",
      "rules-add",
      "sample-dismiss",
      "sample-start-fresh",
      "theme-toggle",
      "topbar-*",
      "topbar-more"
    ],
    "untestided": 37
  },
  "/artifacts": {
    "testids": [
      "add-menu-caret",
      "add-transaction-btn",
      "artifact-delete-art-*",
      "artifact-delete-art-dining",
      "artifact-delete-art-grocery",
      "artifact-delete-art-receipt",
      "artifact-delete-art-shop-*",
      "artifact-delete-art-shop-aov",
      "artifact-delete-art-shop-costs",
      "artifact-download-art-*",
      "artifact-download-art-dining",
      "artifact-download-art-grocery",
      "artifact-download-art-receipt",
      "artifact-download-art-shop-*",
      "artifact-download-art-shop-aov",
      "artifact-download-art-shop-costs",
      "artifact-menu-btn-art-*",
      "artifact-menu-btn-art-dining",
      "artifact-menu-btn-art-grocery",
      "artifact-menu-btn-art-receipt",
      "artifact-menu-btn-art-shop-*",
      "artifact-menu-btn-art-shop-aov",
      "artifact-menu-btn-art-shop-costs",
      "artifacts-next",
      "artifacts-prev",
      "help-button",
      "member-*",
      "profile-switch-btn",
      "sample-dismiss",
      "sample-start-fresh",
      "theme-toggle",
      "topbar-*",
      "topbar-more"
    ],
    "untestided": 27
  },
  "/activity": {
    "testids": [
      "activity-entity-filter",
      "add-menu-caret",
      "add-transaction-btn",
      "help-button",
      "member-*",
      "profile-switch-btn",
      "sample-dismiss",
      "sample-start-fresh",
      "theme-toggle",
      "topbar-*",
      "topbar-more"
    ],
    "untestided": 16
  },
  "/settings": {
    "testids": [
      "add-menu-caret",
      "add-transaction-btn",
      "help-button",
      "member-*",
      "profile-switch-btn",
      "sample-dismiss",
      "sample-start-fresh",
      "theme-toggle",
      "topbar-*",
      "topbar-more"
    ],
    "untestided": 49
  },
  "/help": {
    "testids": [
      "add-menu-caret",
      "add-transaction-btn",
      "help-button",
      "help-guided-setup",
      "member-*",
      "profile-switch-btn",
      "sample-dismiss",
      "sample-start-fresh",
      "theme-toggle",
      "topbar-*",
      "topbar-more"
    ],
    "untestided": 20
  },
  "/about": {
    "testids": [
      "add-menu-caret",
      "add-transaction-btn",
      "help-button",
      "member-*",
      "profile-switch-btn",
      "sample-dismiss",
      "sample-start-fresh",
      "theme-toggle",
      "topbar-*",
      "topbar-more"
    ],
    "untestided": 19
  },
  "/customize": {
    "testids": [
      "add-menu-caret",
      "add-transaction-btn",
      "fb-group-*",
      "fb-group-Budgets",
      "fb-group-Core money",
      "fb-group-Counts",
      "fb-group-Credit health",
      "fb-group-Debts",
      "fb-group-Goals",
      "fb-group-Health factors",
      "fb-group-Net worth",
      "fb-group-Reports",
      "fb-group-Smart features",
      "fb-search",
      "help-button",
      "member-*",
      "mol-edit-*",
      "mol-edit-debt_to_asset_pct",
      "mol-edit-safe_to_spend",
      "mol-new-create",
      "mol-new-formula",
      "mol-new-name",
      "profile-switch-btn",
      "sample-dismiss",
      "sample-start-fresh",
      "theme-toggle",
      "topbar-*",
      "topbar-more"
    ],
    "untestided": 33
  },
  "/fields": {
    "testids": [
      "add-menu-caret",
      "add-transaction-btn",
      "fld-delete-btn-cf-acct-*",
      "fld-delete-btn-cf-txn-*",
      "fld-delete-btn-cf-txn-project",
      "fld-menu-btn-cf-acct-*",
      "fld-menu-btn-cf-txn-*",
      "fld-menu-btn-cf-txn-project",
      "help-button",
      "member-*",
      "profile-switch-btn",
      "sample-dismiss",
      "sample-start-fresh",
      "theme-toggle",
      "topbar-*",
      "topbar-more"
    ],
    "untestided": 27
  },
  "/workflows": {
    "testids": [
      "add-menu-caret",
      "add-transaction-btn",
      "cond-var-*",
      "help-button",
      "member-*",
      "profile-switch-btn",
      "sample-dismiss",
      "sample-start-fresh",
      "theme-toggle",
      "topbar-*",
      "topbar-more",
      "wf-delete-btn-wf-baby",
      "wf-delete-btn-wf-coffee",
      "wf-delete-btn-wf-flag-big",
      "wf-delete-btn-wf-review",
      "wf-menu-btn-wf-baby",
      "wf-menu-btn-wf-coffee",
      "wf-menu-btn-wf-flag-big",
      "wf-menu-btn-wf-review",
      "wf-var-insert"
    ],
    "untestided": 53
  },
  "/appearance": {
    "testids": [
      "add-menu-caret",
      "add-transaction-btn",
      "help-button",
      "member-*",
      "profile-switch-btn",
      "sample-dismiss",
      "sample-start-fresh",
      "theme-toggle",
      "topbar-*",
      "topbar-more"
    ],
    "untestided": 55
  },
  "/setup": {
    "testids": [
      "add-menu-caret",
      "add-transaction-btn",
      "help-button",
      "member-*",
      "profile-switch-btn",
      "sample-dismiss",
      "sample-start-fresh",
      "setup-*",
      "theme-toggle",
      "topbar-*",
      "topbar-more"
    ],
    "untestided": 16
  },
  "/credit": {
    "testids": [
      "add-menu-caret",
      "add-transaction-btn",
      "credit-limit-edit-acct-*",
      "credit-limit-edit-acct-card",
      "credit-toggle-*",
      "help-button",
      "member-*",
      "profile-switch-btn",
      "sample-dismiss",
      "sample-start-fresh",
      "theme-toggle",
      "topbar-*",
      "topbar-more"
    ],
    "untestided": 15
  },
  "/loans": {
    "testids": [
      "add-menu-caret",
      "add-transaction-btn",
      "help-button",
      "member-*",
      "profile-switch-btn",
      "sample-dismiss",
      "sample-start-fresh",
      "theme-toggle",
      "topbar-*",
      "topbar-more"
    ],
    "untestided": 23
  },
  "/bills": {
    "testids": [
      "add-menu-caret",
      "add-transaction-btn",
      "bills-smart-open",
      "cal-next",
      "cal-prev",
      "help-button",
      "member-*",
      "profile-switch-btn",
      "sample-dismiss",
      "sample-start-fresh",
      "smart-action-SMART-*",
      "smart-badge-SMART-*",
      "smart-dismiss",
      "smart-section-action",
      "smart-strip-toggle",
      "smart-strip-viewall",
      "theme-toggle",
      "topbar-*",
      "topbar-more"
    ],
    "untestided": 40
  },
  "/subscriptions": {
    "testids": [
      "add-menu-caret",
      "add-transaction-btn",
      "help-button",
      "member-*",
      "profile-switch-btn",
      "sample-dismiss",
      "sample-start-fresh",
      "smart-action-SMART-*",
      "smart-dismiss",
      "smart-section-action",
      "smart-strip-toggle",
      "smart-strip-viewall",
      "sub-cancel-select-*",
      "sub-cancel-select-gas",
      "sub-cancel-select-gas-(priyas-car)",
      "sub-cancel-select-household-&-*",
      "sub-cancel-select-movies-&-fun",
      "sub-cancel-select-phones-(two-lines)",
      "sub-cancel-select-shop-*",
      "sub-cancel-select-youtube-premium",
      "sub-howto-cancel-*",
      "sub-howto-cancel-gas",
      "sub-howto-cancel-gas-(priyas-car)",
      "sub-howto-cancel-household-&-*",
      "sub-howto-cancel-movies-&-fun",
      "sub-howto-cancel-phones-(two-lines)",
      "sub-howto-cancel-shop-*",
      "sub-howto-cancel-youtube-premium",
      "sub-ignore-*",
      "sub-ignore-gas",
      "sub-ignore-gas-(priyas-car)",
      "sub-ignore-household-&-*",
      "sub-ignore-movies-&-fun",
      "sub-ignore-phones-(two-lines)",
      "sub-ignore-shop-*",
      "sub-ignore-youtube-premium",
      "subs-detect-prefs-toggle",
      "subs-see-insights-link",
      "subs-select-all-btn",
      "theme-toggle",
      "topbar-*",
      "topbar-more"
    ],
    "untestided": 50
  },
  "/insights": {
    "testids": [
      "add-menu-caret",
      "add-transaction-btn",
      "assistant-*",
      "assistant-new-chat",
      "assistant-see-*",
      "assistant-send",
      "help-button",
      "member-*",
      "period-pill",
      "profile-switch-btn",
      "sample-dismiss",
      "sample-start-fresh",
      "theme-toggle",
      "topbar-*",
      "topbar-more"
    ],
    "untestided": 46
  },
  "/smart": {
    "testids": [
      "add-menu-caret",
      "add-transaction-btn",
      "help-button",
      "member-*",
      "profile-switch-btn",
      "sample-dismiss",
      "sample-start-fresh",
      "smart-action-SMART-*",
      "smart-density",
      "smart-digest-cadence",
      "smart-disable-all",
      "smart-dismiss",
      "smart-enable-all",
      "smart-enable-free",
      "smart-group-*",
      "smart-group-bills",
      "smart-group-budgets",
      "smart-group-goals",
      "smart-group-todos",
      "smart-insights-next",
      "smart-insights-prev",
      "theme-toggle",
      "topbar-*",
      "topbar-more"
    ],
    "untestided": 16
  },
  "/members": {
    "testids": [
      "add-menu-caret",
      "add-transaction-btn",
      "help-button",
      "member-*",
      "member-delete-m-marcus",
      "member-delete-m-priya",
      "member-make-default-m-priya",
      "member-menu-btn-m-marcus",
      "member-menu-btn-m-priya",
      "member-set-pin-m-marcus",
      "member-set-pin-m-priya",
      "member-view-m-marcus",
      "member-view-m-priya",
      "profile-switch-btn",
      "sample-dismiss",
      "sample-start-fresh",
      "theme-toggle",
      "topbar-*",
      "topbar-more"
    ],
    "untestided": 18
  },
  "/split": {
    "testids": [
      "add-menu-caret",
      "add-transaction-btn",
      "help-button",
      "member-*",
      "profile-switch-btn",
      "sample-dismiss",
      "sample-start-fresh",
      "theme-toggle",
      "topbar-*",
      "topbar-more"
    ],
    "untestided": 24
  },
  "/widget-builder": {
    "testids": [
      "add-menu-caret",
      "add-transaction-btn",
      "help-button",
      "member-*",
      "profile-switch-btn",
      "sample-dismiss",
      "sample-start-fresh",
      "theme-toggle",
      "topbar-*",
      "topbar-more",
      "vb-publish",
      "vb-redo",
      "vb-save",
      "vb-undo"
    ],
    "untestided": 53
  },
  "/widget-manager": {
    "testids": [
      "add-menu-caret",
      "add-transaction-btn",
      "help-button",
      "member-*",
      "profile-switch-btn",
      "sample-dismiss",
      "sample-start-fresh",
      "theme-toggle",
      "topbar-*",
      "topbar-more"
    ],
    "untestided": 158
  },
  "/documents": {
    "testids": [
      "add-menu-caret",
      "add-transaction-btn",
      "cadence-reminder-btn",
      "csv-file-picker",
      "extract-ai-btn",
      "help-button",
      "member-*",
      "profile-switch-btn",
      "sample-dismiss",
      "sample-start-fresh",
      "theme-toggle",
      "topbar-*",
      "topbar-more"
    ],
    "untestided": 29
  },
  "/duplicates": {
    "testids": [
      "add-menu-caret",
      "add-transaction-btn",
      "help-button",
      "member-*",
      "profile-switch-btn",
      "sample-dismiss",
      "sample-start-fresh",
      "theme-toggle",
      "topbar-*",
      "topbar-more"
    ],
    "untestided": 17
  },
  "/plans": {
    "testids": [
      "add-menu-caret",
      "add-transaction-btn",
      "help-button",
      "member-*",
      "profile-switch-btn",
      "sample-dismiss",
      "sample-start-fresh",
      "theme-toggle",
      "topbar-*",
      "topbar-more"
    ],
    "untestided": 16
  },
  "/p/side-hustle": {
    "testids": [
      "add-menu-caret",
      "add-transaction-btn",
      "cpw-delete-w-*",
      "cpw-delete-w-sh-*",
      "cpw-delete-w-sh-savings",
      "cpw-delete-w-surplus",
      "cpw-edit-w-*",
      "cpw-edit-w-sh-*",
      "cpw-edit-w-sh-savings",
      "cpw-edit-w-surplus",
      "cpw-menu-btn-w-*",
      "cpw-menu-btn-w-sh-*",
      "cpw-menu-btn-w-sh-savings",
      "cpw-menu-btn-w-surplus",
      "help-button",
      "member-*",
      "profile-switch-btn",
      "sample-dismiss",
      "sample-start-fresh",
      "theme-toggle",
      "topbar-*",
      "topbar-more"
    ],
    "untestided": 28
  },
  "/p/priya-business": {
    "testids": [
      "add-menu-caret",
      "add-transaction-btn",
      "cpw-delete-w-pb-*",
      "cpw-delete-w-pb-costs",
      "cpw-delete-w-pb-costs-live",
      "cpw-delete-w-pb-note",
      "cpw-delete-w-pb-orders",
      "cpw-delete-w-pb-pnl",
      "cpw-delete-w-pb-recent",
      "cpw-delete-w-pb-rev",
      "cpw-delete-w-pb-sales",
      "cpw-delete-w-pb-savings",
      "cpw-delete-w-pb-tax",
      "cpw-edit-w-pb-*",
      "cpw-edit-w-pb-costs",
      "cpw-edit-w-pb-costs-live",
      "cpw-edit-w-pb-note",
      "cpw-edit-w-pb-orders",
      "cpw-edit-w-pb-pnl",
      "cpw-edit-w-pb-recent",
      "cpw-edit-w-pb-rev",
      "cpw-edit-w-pb-sales",
      "cpw-edit-w-pb-savings",
      "cpw-edit-w-pb-tax",
      "cpw-menu-btn-w-pb-*",
      "cpw-menu-btn-w-pb-costs",
      "cpw-menu-btn-w-pb-costs-live",
      "cpw-menu-btn-w-pb-note",
      "cpw-menu-btn-w-pb-orders",
      "cpw-menu-btn-w-pb-pnl",
      "cpw-menu-btn-w-pb-recent",
      "cpw-menu-btn-w-pb-rev",
      "cpw-menu-btn-w-pb-sales",
      "cpw-menu-btn-w-pb-savings",
      "cpw-menu-btn-w-pb-tax",
      "help-button",
      "member-*",
      "profile-switch-btn",
      "sample-dismiss",
      "sample-start-fresh",
      "theme-toggle",
      "topbar-*",
      "topbar-more"
    ],
    "untestided": 61
  },
  "/p/marcus-hobbies": {
    "testids": [
      "add-menu-caret",
      "add-transaction-btn",
      "cpw-delete-w-mh-*",
      "cpw-delete-w-mh-note",
      "cpw-delete-w-mh-recent",
      "cpw-delete-w-mh-trend",
      "cpw-delete-w-mh-wsb",
      "cpw-delete-w-mh-wsbval",
      "cpw-edit-w-mh-*",
      "cpw-edit-w-mh-note",
      "cpw-edit-w-mh-recent",
      "cpw-edit-w-mh-trend",
      "cpw-edit-w-mh-wsb",
      "cpw-edit-w-mh-wsbval",
      "cpw-menu-btn-w-mh-*",
      "cpw-menu-btn-w-mh-note",
      "cpw-menu-btn-w-mh-recent",
      "cpw-menu-btn-w-mh-trend",
      "cpw-menu-btn-w-mh-wsb",
      "cpw-menu-btn-w-mh-wsbval",
      "help-button",
      "member-*",
      "profile-switch-btn",
      "sample-dismiss",
      "sample-start-fresh",
      "theme-toggle",
      "topbar-*",
      "topbar-more"
    ],
    "untestided": 37
  }
}
